{"cameraMode":{"drawMode":0,"name":"Shaded","section":"Shading Mode"},"sceneLighting":true,"audioPlay":false,"sceneViewState":{"showFog":true,"showMaterialUpdate":false,"showSkybox":true,"showFlares":true,"showImageEffects":true,"showParticleSystems":true},"in2DMode":false,"pivot":{"x":-3.2740657329559328,"y":4.26659631729126,"z":-71.0592269897461},"rotation":{"x":0.017246322706341745,"y":-0.5878247618675232,"z":0.012517076916992665,"w":0.8087502121925354},"size":8.7098388671875,"orthographic":false}